llm_code_context_generator/__init__.py
llm_code_context_generator/main.py
llm_code_context_generator-0.1.5.dist-info/licenses/LICENSE
llm_code_context_generator-0.1.5.dist-info/METADATA
llm_code_context_generator-0.1.5.dist-info/WHEEL
llm_code_context_generator-0.1.5.dist-info/entry_points.txt
llm_code_context_generator-0.1.5.dist-info/top_level.txt
llm_code_context_generator-0.1.5.dist-info/RECORD
