Metadata-Version: 2.4
Name: llm-code-context-generator
Version: 0.1.5
Summary: A tool to generate comprehensive context for LLMs from any codebase.
Author-email: Masoud Karimi <masoud.develop@gmail.com>
License: MIT License
Project-URL: Homepage, https://github.com/masoudkaarimi/llm-code-context-generator
Project-URL: Bug Tracker, https://github.com/masoudkaarimi/llm-code-context-generator/issues
Keywords: llm,ai,context,developer-tools,cli
Classifier: Programming Language :: Python :: 3
Classifier: License :: OSI Approved :: MIT License
Classifier: Operating System :: OS Independent
Classifier: Topic :: Software Development :: Build Tools
Requires-Python: >=3.8
License-File: LICENSE
Requires-Dist: pathspec
Requires-Dist: tqdm
Requires-Dist: tomli; python_version < "3.11"
Dynamic: license-file
